flask_rollbar
