Metadata-Version: 1.0
Name: flask-rollbar
Version: 1.0.1
Summary: A sane configuration for Rollbar for Flask selfishly based on my own needs
Home-page: https://github.com/angstwad/flask-rollbar
Author: Paul Durivage
Author-email: pauldurivage@gmail.com
License: Apache v2.0
Platform: UNKNOWN
